{"id":"KU536MDQFVW6N","name":"]ZUK6V@(U0TKF_UKG72H7R9","size":127712,"btime":1632894429731,"mtime":1632893914753,"ext":"jpg","tags":[],"folders":[],"isDeleted":false,"url":"","annotation":"","modificationTime":1632894430675,"height":1544,"width":1280,"lastModified":1632894430856,"palettes":[{"color":[250,250,250],"ratio":61},{"color":[191,163,165],"ratio":18},{"color":[67,59,64],"ratio":10},{"color":[141,116,143],"ratio":2.36},{"color":[132,107,105],"ratio":2.21},{"color":[197,165,203],"ratio":2.15},{"color":[177,143,189],"ratio":1.27},{"color":[206,196,201],"ratio":1.21}]}