{"id":"KN9W74VY7EO3J","name":"旧都なぎ @QTONAGI  Twitter","size":968468,"btime":1617947551878,"mtime":1617947551878,"ext":"png","tags":[],"folders":[],"isDeleted":false,"url":"https://www.pinterest.com/pin/659847782890619033/","annotation":"","modificationTime":1617947551870,"width":636,"height":900,"noThumbnail":true,"lastModified":1617947552016,"palettes":[{"color":[59,31,21],"ratio":45},{"color":[229,229,231],"ratio":28},{"color":[150,119,102],"ratio":7},{"color":[107,72,52],"ratio":6},{"color":[168,171,174],"ratio":4.68},{"color":[115,110,101],"ratio":2.93},{"color":[197,159,146],"ratio":1.99},{"color":[149,145,151],"ratio":1},{"color":[101,88,85],"ratio":0.83},{"color":[195,134,96],"ratio":0.35}]}