{"id":"KW64J5TP9OWQ6","name":"40 Pinterest","size":11700,"btime":1637310726253,"mtime":1637310726253,"ext":"jpg","tags":[],"folders":[],"isDeleted":false,"url":"https://www.pinterest.com/pin/1759287344497962/","annotation":"","modificationTime":1637310726205,"noThumbnail":true,"width":209,"height":200,"lastModified":1637310726494,"palettes":[{"color":[27,27,31],"ratio":49},{"color":[229,223,218],"ratio":24},{"color":[127,111,106],"ratio":11},{"color":[75,65,66],"ratio":6},{"color":[84,92,108],"ratio":3.47},{"color":[181,158,141],"ratio":2.49},{"color":[153,149,149],"ratio":0.79}]}