{"id":"KLTCOL94VOB3Q","name":"KLTCIST656IG2","size":227209,"btime":1614770655086,"mtime":1614770655086,"ext":"jpg","tags":[],"folders":["KLTCISH5XXMMF"],"isDeleted":false,"url":"https://www.pinterest.com/pin/788904059720898202/","annotation":"","modificationTime":1614770262051,"noThumbnail":true,"width":900,"height":1385,"lastModified":1614772210204,"palettes":[{"color":[230,231,236],"ratio":75},{"color":[146,138,152],"ratio":8},{"color":[172,173,184],"ratio":6},{"color":[192,192,202],"ratio":4.68},{"color":[89,79,92],"ratio":1.72},{"color":[192,174,189],"ratio":1.51},{"color":[155,164,178],"ratio":0.39}]}