{"id":"KLTD44X6UWGTA","name":"KLTCISZRZ6DUY","size":1208433,"btime":1614771427227,"mtime":1614771427228,"ext":"png","tags":[],"folders":["KLTCISH5XXMMF"],"isDeleted":false,"url":"https://www.pinterest.com/pin/788904059718973554/","annotation":"","modificationTime":1614770262031,"height":1612,"width":875,"lastModified":1614772210515,"palettes":[{"color":[43,35,29],"ratio":48},{"color":[227,216,203],"ratio":21},{"color":[137,114,97],"ratio":13},{"color":[92,72,59],"ratio":9},{"color":[190,156,120],"ratio":3.36},{"color":[106,101,94],"ratio":1.42},{"color":[162,158,145],"ratio":0.85},{"color":[101,90,92],"ratio":0.68},{"color":[178,124,89],"ratio":0.56},{"color":[156,146,149],"ratio":0.46}]}