{"id":"KMU5N6DOQTD8I","name":"图像","size":828984,"btime":1616995958036,"mtime":1616995958037,"ext":"jpg","tags":[],"folders":[],"isDeleted":false,"url":"https://twitter.com/Zhibujiloom/status/1368297444400795649/photo/1","annotation":"","modificationTime":1616995958028,"width":2439,"height":4063,"lastModified":1616995958498,"palettes":[{"color":[227,227,219],"ratio":69},{"color":[70,45,47],"ratio":19},{"color":[162,139,129],"ratio":5},{"color":[134,70,71],"ratio":4.97},{"color":[206,186,175],"ratio":0.6}]}